project3/run/modules.v
module rf(input clk, rst, regwrite, input[31:0] in_val, input [2:0] readaddress1, readaddress2, writeaddress, input [15:0] write_data, output [15:0] print_rdata1, print_rdata2);
    reg [15:0] internal_memory [7:0];		// internal memory to be loaded
    integer i;					 
    always @(posedge clk) begin
        {internal_memory[0], internal_memory[6]} = in_val; // initialize internal memory, $0, $6 are constant 0
        if(~rst) begin 
            for (i=0; i<8; i=i+1) 
                internal_memory[i] = 16'b0; 
        end	
        else if(regwrite) 
            internal_memory[writeaddress] = write_data;
    end						
    assign print_rdata1 = internal_memory[readaddress1];	// save internal memory in print_rdata1	
    assign print_rdata2 = internal_memory[readaddress2];	// save internal memory in print_rdata2	
endmodule

module PC_Reg(input [12:0] PC_in,input rst,clk,output reg [12:0] PC_out);
    always @(posedge clk)begin
        if (~rst)					// if the reset value is 0, PC value will be 0
            PC_out = 0;
        else if (PC_out>22)				// if the current PC value is greater than 22, the value will be 0 
            PC_out = 0;					
        else
            PC_out = PC_in;				// on the other cases, PC value will have next PC value
    end
endmodule

module control(input[2:0] opcode, input reset, output reg[1:0] regDst,memToReg,aluOp, output reg jump,branch,memRead,memWrite,aluSrc,regWrite);  
    always @(*) begin  			
        if(reset == 0) begin  
            regDst = 2'b00; aluSrc = 1'b0; memToReg = 2'b00; regWrite = 1'b0; memRead = 1'b0; memWrite = 1'b0;  branch = 1'b0;   
            aluOp = 2'b00; jump = 1'b0;
        end  
        else begin  
            case(opcode)   				
                3'b000: begin 				// add
                    regDst = 2'b01; aluSrc = 1'b0; memToReg = 2'b00; regWrite = 1'b1; memRead = 1'b0; memWrite = 1'b0;  branch = 1'b0;   
                    aluOp = 2'b00; jump = 1'b0;
                end  
                3'b001: begin  				// sli
                    regDst = 2'b00; aluSrc = 1'b1; memToReg = 2'b00; regWrite = 1'b1; memRead = 1'b0; memWrite = 1'b0;  branch = 1'b0;   
                    aluOp = 2'b10; jump = 1'b0;
                end
                3'b010: begin  				// j
                    regDst = 2'b00; aluSrc = 1'b0; memToReg = 2'b00; regWrite = 1'b0; memRead = 1'b0; memWrite = 1'b0;  branch = 1'b0;   
                    aluOp = 2'b00; jump = 1'b1;
                end  
                3'b011: begin   			// jal
                    regDst = 2'b10; aluSrc = 1'b0; memToReg = 2'b10; regWrite = 1'b1; memRead = 1'b0; memWrite = 1'b0;  branch = 1'b0;   
                    aluOp = 2'b00; jump = 1'b1;
                end  
                3'b100: begin 				// lw
                    regDst = 2'b00; aluSrc = 1'b1; memToReg = 2'b01; regWrite = 1'b1; memRead = 1'b1; memWrite = 1'b0;  branch = 1'b0;   
                    aluOp = 2'b11; jump = 1'b0;
                end
                3'b101: begin 				// sw
                    regDst = 2'b00; aluSrc = 1'b1; memToReg = 2'b00; regWrite = 1'b0; memRead = 1'b0; memWrite = 1'b1;  branch = 1'b0;   
                    aluOp = 2'b11; jump = 1'b0;
                end
                3'b110: begin   			// beq
                    regDst = 2'b00; aluSrc = 1'b0; memToReg = 2'b00; regWrite = 1'b0; memRead = 1'b0; memWrite = 1'b0;  branch = 1'b1;   
                    aluOp = 2'b01; jump = 1'b0;
                end
                3'b111: begin 				// addi
                    regDst = 2'b00; aluSrc = 1'b1; memToReg = 2'b00; regWrite = 1'b1; memRead = 1'b0; memWrite = 1'b0;  branch = 1'b0;   
                    aluOp = 2'b11; jump = 1'b0;
                end
            endcase  
        end  
    end  
endmodule

module ALUControl(output reg[2:0] ALU_Control,input [1:0] ALUop,input [3:0] Function);
    wire [5:0] ALUControlIn;
    assign ALUControlIn = {ALUop, Function};  	// ALU op (2bit) + Function (4bit)
    always @(ALUControlIn) begin
        casex (ALUControlIn)  			// ALU ctrl output bit according to each ALUControlIn bit
            6'b11xxxx: ALU_Control=3'b000;   6'b01xxxx: ALU_Control=3'b001;  
            6'b00_0000: ALU_Control=3'b000;  6'b00_0001: ALU_Control=3'b001;  
            6'b00_0010: ALU_Control=3'b010;  6'b00_0011: ALU_Control=3'b011;  
            6'b00_0100: ALU_Control=3'b100;  6'b00_0101: ALU_Control=3'b101;
            6'b00_0110: ALU_Control=3'b110;  6'b10xxxx: ALU_Control=3'b100;
        endcase  
    end
 endmodule

module alu(input [15:0] a, input [15:0] b, input [2:0] alu_control,output reg [15:0] result,output zero);  
    always @(*) begin   
        case(alu_control)  
            3'b000 : result = a + b; 3'b001 : result = a - b;	// add, sub
            3'b010 : result = a & b; 3'b011 : result = a | b;   // and, or
            3'b101 : result = a * b; 3'b110 : result = a / b;   // mul, div
            3'b100 : begin if (a<b) result = 16'd1;             // slt
                        else result = 16'd0; 
                    end
        endcase  
    end  
    assign zero = (result==16'd0) ? 1'b1: 1'b0;  // if the result value is 0, zero becomes 1
endmodule

module JR_Control( input[1:0] aluOp,input [3:0] function0,output JRControl);
    assign JRControl = ({aluOp,function0}==6'b001000) ? 1'b1 : 1'b0;	// JR control will be 1 when '{aluOp,function0}==6'b001000'
endmodule					

module and_gate(a, b, c);
    output a;
    input b,c;
    
    assign a = b & c;
endmodule

module sign_extend(input [6:0] in1,output [15:0] out1);
    assign out1= {9'b0,in1[6:0]};				// extend 7bit to 16 bit for the addition
endmodule

module add#(parameter data=13)
(input [12:0] a,input [data-1:0] b,output [data-1:0] result);  
    assign result = a + b; 				// add the value
endmodule

module mux2X1#(parameter data=16)
(input[data-1:0] in0,in1,input sel,output [data-1:0]out0);
    assign out0= (sel) ? in1 : in0;				// 2x1 mux 
endmodule					

module mux3X1#(parameter data=16)
(input [data-1:0] in0, in1, in2,input [1:0] sel, output reg [data-1:0] out0);                
    always @(*) begin 
        case(sel)						// 3x1 mux
            2'b00 : out0 = in0;					
            2'b01 : out0 = in1;					
            2'b10 : out0 = in2;					
        endcase
    end
endmodule

project3/run/data.v
module data_Memory  
(input clk, rst, input[383:0] in_data, input mem_read, mem_write_en,input [15:0] mem_access_addr,input [15:0] mem_write_data,output [15:0] mem_read_data);  
    integer i;  
    reg [15:0] internal_mem [23:0];  
    wire [4:0] mem_addr = mem_access_addr[4:0]; // store data memory address (0~23)  
    
    always @(posedge clk) begin  
        if (~rst)
            {internal_mem[0], internal_mem[1], internal_mem[2], internal_mem[3], internal_mem[4], internal_mem[5], internal_mem[6], internal_mem[7], internal_mem[8], internal_mem[9], internal_mem[10], internal_mem[11], internal_mem[12], internal_mem[13], internal_mem[14], internal_mem[15], internal_mem[16], internal_mem[17], internal_mem[18], internal_mem[19], internal_mem[20], internal_mem[21], internal_mem[22], internal_mem[23]} = in_data;
            // initialize internal_mem
        else if (mem_write_en)  			
            internal_mem[mem_addr] = mem_write_data;  // initialize new value for sw case
    end  

    assign mem_read_data = (mem_read==1'b1) ? internal_mem[mem_addr]: 16'd0;    // load value for lw case
endmodule

project3/run/instr.v
module inst_mem (input [12:0] pc, input[383:0] in_instr, output reg [15:0] current_instruction); 	
    reg [15:0] rom[23:0];  	
    		    
    always @(*) begin
        {rom[0], rom[1], rom[2], rom[3], rom[4], rom[5], rom[6], rom[7], rom[8], rom[9], rom[10], rom[11], rom[12], rom[13], rom[14], rom[15], rom[16], rom[17], rom[18], rom[19], rom[20], rom[21], rom[22], rom[23]} = in_instr;
        // initialize rom
        if(pc<23)
            current_instruction = rom[pc[4:0]];  
        else
            current_instruction = rom[23];  
    end
 endmodule

project3/run/MIPS16.v
module MIPS16(input clk, rst, input [383:0] in_instr, in_data, input[31:0] in_val, output [15:0] current_instruction);
    wire jump, branch, mem_read, mem_write, alu_src, reg_write, JRout, andout, zero;   
    wire [1:0] reg_dst,mem_to_reg,alu_op;  
    wire [2:0] writeaddress,ALU_Control;  
    wire [12:0] PC_out,PC_out1, PC_out2,PC_out3,PC_out4,PC_in; 
    wire [15:0] reg_write_data,write_data,print_rdata1, print_rdata2,inst_extend,aludata2,ALUresult,mem_read_data,mux6out; 

    PC_Reg PC(PC_in,rst,clk,PC_out);    // initialize Program Counter
    inst_mem instructionMemory(PC_out,in_instr,current_instruction);   // instruction will be executed through the PC from the input instruction memeory 	
    data_Memory data_memory( clk, rst, in_data, mem_read, mem_write, ALUresult, print_rdata2,mem_read_data);    // data memory will be read or written by RF information
    add #(13) Add1(PC_out, 13'b1, PC_out1);     // PC increases by 1 each time	
    and_gate And (andout, branch, zero);    // branch & zero, it will be operated as sel in MUX3					
    rf register_file(clk, rst, reg_write, in_val, current_instruction[12:10], current_instruction[9:7], writeaddress, reg_write_data, print_rdata1, print_rdata2);		// Register File gets the instruction and updates internal memory
    control CONTROL(current_instruction[15:13],rst,reg_dst,mem_to_reg,alu_op,jump, branch, mem_read, mem_write, alu_src, reg_write);    // control module for 16bit MIPS processor
    sign_extend signExtend(current_instruction[6:0],inst_extend);	// extending bit is needed for the addition (7bit to 16bit)
    ALUControl aluControl(ALU_Control, alu_op, current_instruction[3:0]);	//ALU Control is needed for selecting the value in the alu module
    alu ALU(print_rdata1, aludata2, ALU_Control, ALUresult, zero);   // alu module controls the value from the registers
    JR_Control jrControl(alu_op, current_instruction[3:0], JRout);    // JR control module is needed for jump instruction
    add #(13) Add2(PC_out1, inst_extend[12:0],PC_out2); 		// addition between the PC_out1 and the sign-extended instructoin

    mux3X1 #(3) MUX1(current_instruction[9:7], current_instruction[6:4], 3'b111, reg_dst, writeaddress);    // 3 to 1 mux for write_register address
    mux2X1 #(16) MUX2(print_rdata2, inst_extend, alu_src, aludata2); // 2 to 1 mux for alu data

    mux2X1 #(13) MUX3(PC_out1, PC_out2, andout, PC_out3);   /* these muxes are for pc */ 
    mux2X1 #(13) MUX4(PC_out3, current_instruction[12:0], jump, PC_out4);
    mux2X1 #(13) MUX5(PC_out4, print_rdata1[12:0], JRout, PC_in);

    mux3X1 #(16) MUX6(ALUresult, mem_read_data, {3'b000,PC_out1}, mem_to_reg, mux6out);   /* these muxes are for write_data */
    mux2X1 #(16) MUX7(mux6out, 16'b101, JRout, reg_write_data);
endmodule

project3/run/MIPS_tb.v
`timescale 1ns/1ps
module MIPS_tb();
    reg clk, rst;
    reg [383:0] in_instr, in_data; // instruction memory and data memory for implementation
    reg [31:0] in_val; // initial value for $r
    wire [15:0] current_instr;
    MIPS16 cgcpu(clk, rst, in_instr, in_data, in_val, current_instr);
    initial begin
        clk=0; rst=0;
        in_val = 32'b0;
        in_instr = 384'b1001_1001_0000_00011001_1001_1000_00100000_1001_1100_00000000_1001_1001_01001100_0100_0000_00100000_1001_1100_00100100_0000_0000_10000000_1001_1100_00010000_1001_1100_00110110_0000_0000_11011111_0010_0000_00101011_1010_0000_00110100_0000_0000_1111000_010_011_100_01100001_1100_0000_10000000_0000_0000_00000000_0000_0000_00000000_0000_0000_00000000_0000_0000_00000000_0000_0000_00000000_0000_0000_00000000_0000_0000_00000000_0000_0000_00000000_0000_0000_0000;
        // given instruction memory
        in_data = 384'b0000_0000_0000_0000_0000_0000_0010_0011_0000_0000_0000_1001_0000_0000_0011_0001_0000_0000_1100_1001_0000_0000_0011_1100_0000_0000_1101_1011_0000_0000_0000_0111_1110_0001_0010_1000_0101_0011_1100_0101_1001_0111_1000_1001_1101_0011_1101_1111_1011_1001_1001_0001_0000_0100_0110_0101_0001_1100_0101_0110_0001_0010_1110_0100_0110_1000_0011_1001_1111_1000_0010_1011_0011_1101_0111_1001_1011_0000_0111_0001_0010_0001_1110_0110_1101_0000_1100_1010_0111_0111_0000_1110_1111_1101_1011_1001;
        // given data memory
        #2 rst = 1;
        
        #18 $display("The final result of $s3 in memory is: %d", cgcpu.data_memory.internal_mem[3]);	// the final value of $s3
        $finish;
    end					
    always begin
        #0.5 clk=~clk; 
    end					
    always begin
        #1 $display("ID:4260,  at time %t ps, PC = %d, RF[0,1,2,3,4,7] is : %d,%d,%d,%d,%d,%d", $time, cgcpu.PC.PC_out, cgcpu.register_file.internal_memory[0], cgcpu.register_file.internal_memory[1], cgcpu.register_file.internal_memory[2], cgcpu.register_file.internal_memory[3], cgcpu.register_file.internal_memory[4], cgcpu.register_file.internal_memory[7]);    end
    initial begin
        $dumpfile("output.vcd");
        $dumpvars(0);
    end
endmodule

project3/run/output.vcd
$date
	Sat Jun 25 17:22:16 2022
$end
$version
	Icarus Verilog
$end
$timescale
	1ps
$end
$scope module MIPS_tb $end
$var wire 16 ! current_instr [15:0] $end
$var reg 1 " clk $end
$var reg 384 # in_data [383:0] $end
$var reg 384 $ in_instr [383:0] $end
$var reg 32 % in_val [31:0] $end
$var reg 1 & rst $end
$scope module cgcpu $end
$var wire 1 " clk $end
$var wire 384 ' in_data [383:0] $end
$var wire 384 ( in_instr [383:0] $end
$var wire 32 ) in_val [31:0] $end
$var wire 1 & rst $end
$var wire 1 * zero $end
$var wire 3 + writeaddress [2:0] $end
$var wire 16 , reg_write_data [15:0] $end
$var wire 1 - reg_write $end
$var wire 2 . reg_dst [1:0] $end
$var wire 16 / print_rdata2 [15:0] $end
$var wire 16 0 print_rdata1 [15:0] $end
$var wire 16 1 mux6out [15:0] $end
$var wire 1 2 mem_write $end
$var wire 2 3 mem_to_reg [1:0] $end
$var wire 16 4 mem_read_data [15:0] $end
$var wire 1 5 mem_read $end
$var wire 1 6 jump $end
$var wire 16 7 inst_extend [15:0] $end
$var wire 16 8 current_instruction [15:0] $end
$var wire 1 9 branch $end
$var wire 1 : andout $end
$var wire 16 ; aludata2 [15:0] $end
$var wire 1 < alu_src $end
$var wire 2 = alu_op [1:0] $end
$var wire 13 > PC_out4 [12:0] $end
$var wire 13 ? PC_out3 [12:0] $end
$var wire 13 @ PC_out2 [12:0] $end
$var wire 13 A PC_out1 [12:0] $end
$var wire 13 B PC_out [12:0] $end
$var wire 13 C PC_in [12:0] $end
$var wire 1 D JRout $end
$var wire 16 E ALUresult [15:0] $end
$var wire 3 F ALU_Control [2:0] $end
$scope module ALU $end
$var wire 1 * zero $end
$var wire 16 G b [15:0] $end
$var wire 3 H alu_control [2:0] $end
$var wire 16 I a [15:0] $end
$var reg 16 J result [15:0] $end
$upscope $end
$scope module Add1 $end
$var wire 13 K b [12:0] $end
$var wire 13 L result [12:0] $end
$var wire 13 M a [12:0] $end
$upscope $end
$scope module Add2 $end
$var wire 13 N a [12:0] $end
$var wire 13 O b [12:0] $end
$var wire 13 P result [12:0] $end
$upscope $end
$scope module And $end
$var wire 1 : a $end
$var wire 1 * c $end
$var wire 1 9 b $end
$upscope $end
$scope module CONTROL $end
$var wire 3 Q opcode [2:0] $end
$var wire 1 & reset $end
$var reg 2 R aluOp [1:0] $end
$var reg 1 < aluSrc $end
$var reg 1 9 branch $end
$var reg 1 6 jump $end
$var reg 1 5 memRead $end
$var reg 2 S memToReg [1:0] $end
$var reg 1 2 memWrite $end
$var reg 2 T regDst [1:0] $end
$var reg 1 - regWrite $end
$upscope $end
$scope module MUX1 $end
$var wire 3 U in0 [2:0] $end
$var wire 3 V in1 [2:0] $end
$var wire 3 W in2 [2:0] $end
$var wire 2 X sel [1:0] $end
$var reg 3 Y out0 [2:0] $end
$upscope $end
$scope module MUX2 $end
$var wire 1 < sel $end
$var wire 16 Z out0 [15:0] $end
$var wire 16 [ in1 [15:0] $end
$var wire 16 \ in0 [15:0] $end
$upscope $end
$scope module MUX3 $end
$var wire 13 ] in0 [12:0] $end
$var wire 13 ^ in1 [12:0] $end
$var wire 1 : sel $end
$var wire 13 _ out0 [12:0] $end
$upscope $end
$scope module MUX4 $end
$var wire 13 ` in0 [12:0] $end
$var wire 13 a in1 [12:0] $end
$var wire 1 6 sel $end
$var wire 13 b out0 [12:0] $end
$upscope $end
$scope module MUX5 $end
$var wire 13 c in0 [12:0] $end
$var wire 13 d in1 [12:0] $end
$var wire 1 D sel $end
$var wire 13 e out0 [12:0] $end
$upscope $end
$scope module MUX6 $end
$var wire 16 f in0 [15:0] $end
$var wire 16 g in2 [15:0] $end
$var wire 2 h sel [1:0] $end
$var wire 16 i in1 [15:0] $end
$var reg 16 j out0 [15:0] $end
$upscope $end
$scope module MUX7 $end
$var wire 16 k in0 [15:0] $end
$var wire 16 l in1 [15:0] $end
$var wire 1 D sel $end
$var wire 16 m out0 [15:0] $end
$upscope $end
$scope module PC $end
$var wire 13 n PC_in [12:0] $end
$var wire 1 " clk $end
$var wire 1 & rst $end
$var reg 13 o PC_out [12:0] $end
$upscope $end
$scope module aluControl $end
$var wire 2 p ALUop [1:0] $end
$var wire 4 q Function [3:0] $end
$var wire 6 r ALUControlIn [5:0] $end
$var reg 3 s ALU_Control [2:0] $end
$upscope $end
$scope module data_memory $end
$var wire 1 " clk $end
$var wire 384 t in_data [383:0] $end
$var wire 16 u mem_access_addr [15:0] $end
$var wire 1 5 mem_read $end
$var wire 1 2 mem_write_en $end
$var wire 1 & rst $end
$var wire 16 v mem_write_data [15:0] $end
$var wire 16 w mem_read_data [15:0] $end
$var wire 5 x mem_addr [4:0] $end
$upscope $end
$scope module instructionMemory $end
$var wire 384 y in_instr [383:0] $end
$var wire 13 z pc [12:0] $end
$var reg 16 { current_instruction [15:0] $end
$upscope $end
$scope module jrControl $end
$var wire 2 | aluOp [1:0] $end
$var wire 4 } function0 [3:0] $end
$var wire 1 D JRControl $end
$upscope $end
$scope module register_file $end
$var wire 1 " clk $end
$var wire 32 ~ in_val [31:0] $end
$var wire 16 !" print_rdata1 [15:0] $end
$var wire 16 "" print_rdata2 [15:0] $end
$var wire 3 #" readaddress1 [2:0] $end
$var wire 3 $" readaddress2 [2:0] $end
$var wire 1 - regwrite $end
$var wire 1 & rst $end
$var wire 16 %" write_data [15:0] $end
$var wire 3 &" writeaddress [2:0] $end
$var integer 32 '" i [31:0] $end
$upscope $end
$scope module signExtend $end
$var wire 7 (" in1 [6:0] $end
$var wire 16 )" out1 [15:0] $end
$upscope $end
$upscope $end
$upscope $end
$enddefinitions $end
#0
$dumpvars
b0 )"
b0 ("
bx '"
b0 &"
bx %"
b0 $"
b0 #"
bx ""
bx !"
b0 ~
b0 }
b0 |
b0 {
bx z
b100110010000000110011001100000100000100111000000000010011001010011000100000000100000100111000010010000000000100000001001110000010000100111000011011000000000110111110010000000101011101000000011010000000000111100001001110001100001110000001000000000000000000000000000000000000000000000000000000000000000000000000000000000000000000000000000000000000000000000000000000000000000000000000000 y
bx x
b0 w
bx v
bx u
b1000110000000000001001000000000011000100000000110010010000000000111100000000001101101100000000000001111110000100101000010100111100010110010111100010011101001111011111101110011001000100000100011001010001110001010110000100101110010001101000001110011111100000101011001111010111100110110000011100010010000111100110110100001100101001110111000011101111110110111001 t
b0 s
b0 r
b0 q
b0 p
bx o
bx n
bx m
b101 l
bx k
bx j
b0 i
b0 h
b0xxxxxxxxxxxxx g
bx f
bx e
bx d
bx c
bx b
b0 a
bx `
bx _
bx ^
bx ]
bx \
b0 [
bx Z
b0 Y
b0 X
b111 W
b0 V
b0 U
b0 T
b0 S
b0 R
b0 Q
bx P
b0 O
bx N
bx M
bx L
b1 K
bx J
bx I
b0 H
bx G
b0 F
bx E
0D
bx C
bx B
bx A
bx @
bx ?
bx >
b0 =
0<
bx ;
0:
09
b0 8
b0 7
06
05
b0 4
b0 3
02
bx 1
bx 0
bx /
b0 .
0-
bx ,
b0 +
x*
b0 )
b100110010000000110011001100000100000100111000000000010011001010011000100000000100000100111000010010000000000100000001001110000010000100111000011011000000000110111110010000000101011101000000011010000000000111100001001110001100001110000001000000000000000000000000000000000000000000000000000000000000000000000000000000000000000000000000000000000000000000000000000000000000000000000000000 (
b1000110000000000001001000000000011000100000000110010010000000000111100000000001101101100000000000001111110000100101000010100111100010110010111100010011101001111011111101110011001000100000100011001010001110001010110000100101110010001101000001110011111100000101011001111010111100110110000011100010010000111100110110100001100101001110111000011101111110110111001 '
0&
b0 %
b100110010000000110011001100000100000100111000000000010011001010011000100000000100000100111000010010000000000100000001001110000010000100111000011011000000000110111110010000000101011101000000011010000000000111100001001110001100001110000001000000000000000000000000000000000000000000000000000000000000000000000000000000000000000000000000000000000000000000000000000000000000000000000000000 $
b1000110000000000001001000000000011000100000000110010010000000000111100000000001101101100000000000001111110000100101000010100111100010110010111100010011101001111011111101110011001000100000100011001010001110001010110000100101110010001101000001110011111100000101011001111010111100110110000011100010010000111100110110100001100101001110111000011101111110110111001 #
0"
b0 !
$end
#500
b1 C
b1 e
b1 n
b10 +
b10 Y
b10 &"
b1 F
b1 H
b1 s
b1 O
b1 >
b1 b
b1 c
b0 ,
b0 m
b0 %"
b1100100000001 a
b10 U
b1 }
b1 r
b1 q
b1 7
b1 [
b1 )"
b1 ("
b100 Q
b10 $"
b110 #"
1*
b0 x
b1 ?
b1 _
b1 `
b0 1
b0 j
b0 k
b1001100100000001 !
b1001100100000001 8
b1001100100000001 {
b0 d
b0 E
b0 J
b0 f
b0 u
b0 ;
b0 G
b0 Z
b10 @
b10 P
b10 ^
b1 g
b1 A
b1 L
b1 N
b1 ]
b0 B
b0 M
b0 o
b0 z
b1000 '"
b0 0
b0 I
b0 !"
b0 /
b0 \
b0 v
b0 ""
1"
#1000
0"
#1500
b1000 '"
1"
#2000
b100011 ,
b100011 m
b100011 %"
b100011 1
b100011 j
b100011 k
b100011 4
b100011 i
b100011 w
0*
b1 x
b1 E
b1 J
b1 f
b1 u
b0 F
b0 H
b0 s
b1 ;
b1 G
b1 Z
b110001 r
b11 =
b11 R
b11 p
b11 |
15
1-
b1 3
b1 S
b1 h
1<
0"
1&
#2500
b1001 ,
b1001 m
b1001 %"
b1001 1
b1001 j
b1001 k
b1001 4
b1001 i
b1001 w
b10 x
b10 E
b10 J
b10 f
b10 u
b10 C
b10 e
b10 n
b11 +
b11 Y
b11 &"
b10 ;
b10 G
b10 Z
b10 O
b10 >
b10 b
b10 c
b1100110000010 a
b11 U
b10 }
b110010 r
b10 q
b10 7
b10 [
b10 )"
b10 ("
b11 $"
b10 ?
b10 _
b10 `
b1001100110000010 !
b1001100110000010 8
b1001100110000010 {
b100 @
b100 P
b100 ^
b10 g
b10 A
b10 L
b10 N
b10 ]
b1 B
b1 M
b1 o
b1 z
b0 /
b0 \
b0 v
b0 ""
1"
#3000
0"
#3500
b101100 ,
b101100 m
b101100 %"
b0 4
b0 i
b0 w
b101100 1
b101100 j
b101100 k
b1100 x
b11 C
b11 e
b11 n
b100 +
b100 Y
b100 &"
b1001 ;
b1001 G
b1001 Z
b1000000 O
b0 =
b0 R
b0 p
b0 |
05
b0 3
b0 S
b0 h
0<
b1 .
b1 T
b1 X
b100011 d
b101100 E
b101100 J
b101100 f
b101100 u
b11 >
b11 b
b11 c
b100111000000 a
b100 V
b0 }
b0 r
b0 q
b1000000 7
b1000000 [
b1000000 )"
b1000000 ("
b0 Q
b100011 0
b100011 I
b100011 !"
b10 #"
b11 ?
b11 _
b11 `
b100111000000 !
b100111000000 8
b100111000000 {
b1001 /
b1001 \
b1001 v
b1001 ""
b1000011 @
b1000011 P
b1000011 ^
b11 g
b11 A
b11 L
b11 N
b11 ]
b10 B
b10 M
b10 o
b10 z
1"
#4000
0"
#4500
b0 ,
b0 m
b0 %"
1*
b0 1
b0 j
b0 k
b0 x
b0 E
b0 J
b0 f
b0 u
b100 C
b100 e
b100 n
b1 +
b1 Y
b1 &"
b100 F
b100 H
b100 s
b10100 O
b100 >
b100 b
b100 c
b100110010100 a
b1 V
b100 }
b100 r
b100 q
b10100 7
b10100 [
b10100 )"
b10100 ("
b100 ?
b100 _
b100 `
b100110010100 !
b100110010100 8
b100110010100 {
b11000 @
b11000 P
b11000 ^
b100 g
b100 A
b100 L
b100 N
b100 ]
b11 B
b11 M
b11 o
b11 z
1"
#5000
0"
#5500
1:
b0 ,
b0 m
b0 %"
1*
b0 1
b0 j
b0 k
b0 x
b111 C
b111 e
b111 n
b0 +
b0 Y
b0 &"
b1 F
b1 H
b1 s
b10 O
b1 =
b1 R
b1 p
b1 |
19
0-
b0 .
b0 T
b0 X
b0 ;
b0 G
b0 Z
b0 d
b0 E
b0 J
b0 f
b0 u
b111 >
b111 b
b111 c
b10000000010 a
b0 V
b0 U
b10 }
b10010 r
b10 q
b10 7
b10 [
b10 )"
b10 ("
b110 Q
b0 /
b0 \
b0 v
b0 ""
b0 $"
b0 0
b0 I
b0 !"
b1 #"
b111 ?
b111 _
b111 `
b1100010000000010 !
b1100010000000010 8
b1100010000000010 {
b111 @
b111 P
b111 ^
b101 g
b101 A
b101 L
b101 N
b101 ]
b100 B
b100 M
b100 o
b100 z
1"
#6000
0"
#6500
b11010 ,
b11010 m
b11010 %"
0:
0*
b11010 1
b11010 j
b11010 k
b11010 x
b1000 C
b1000 e
b1000 n
b100 +
b100 Y
b100 &"
b1000001 O
b0 =
b0 R
b0 p
b0 |
09
1-
b1 .
b1 T
b1 X
b1001 ;
b1001 G
b1001 Z
b100011 d
b11010 E
b11010 J
b11010 f
b11010 u
b1000 >
b1000 b
b1000 c
b100111000001 a
b100 V
b11 U
b1 }
b1 r
b1 q
b1000001 7
b1000001 [
b1000001 )"
b1000001 ("
b0 Q
b1001 /
b1001 \
b1001 v
b1001 ""
b11 $"
b100011 0
b100011 I
b100011 !"
b10 #"
b1000 ?
b1000 _
b1000 `
b100111000001 !
b100111000001 8
b100111000001 {
b1001001 @
b1001001 P
b1001001 ^
b1000 g
b1000 A
b1000 L
b1000 N
b1000 ]
b111 B
b111 M
b111 o
b111 z
1"
#7000
0"
#7500
b101011 ,
b101011 m
b101011 %"
b101011 1
b101011 j
b101011 k
b1011 x
b101011 E
b101011 J
b101011 f
b101011 u
b1001 C
b1001 e
b1001 n
b11 F
b11 H
b11 s
b1000011 O
b1001 >
b1001 b
b1001 c
b100111000011 a
b11 }
b11 r
b11 q
b1000011 7
b1000011 [
b1000011 )"
b1000011 ("
b1001 ?
b1001 _
b1001 `
b100111000011 !
b100111000011 8
b100111000011 {
b1001100 @
b1001100 P
b1001100 ^
b1001 g
b1001 A
b1001 L
b1001 N
b1001 ]
b1000 B
b1000 M
b1000 o
b1000 z
1"
#8000
0"
#8500
1*
b1010 ,
b1010 m
b1010 %"
b1010 1
b1010 j
b1010 k
b0 x
b1101 C
b1101 e
b1101 n
b111 +
b111 Y
b111 &"
b1101 O
16
b10 3
b10 S
b10 h
b10 .
b10 T
b10 X
b0 ;
b0 G
b0 Z
b0 d
b0 E
b0 J
b0 f
b0 u
b1101 >
b1101 b
b1101 c
b1101 a
b0 V
b0 U
b1101 }
b1101 r
b1101 q
b1101 7
b1101 [
b1101 )"
b1101 ("
b11 Q
b0 /
b0 \
b0 v
b0 ""
b0 $"
b0 0
b0 I
b0 !"
b0 #"
b1010 ?
b1010 _
b1010 `
b110000000001101 !
b110000000001101 8
b110000000001101 {
b10111 @
b10111 P
b10111 ^
b1010 g
b1010 A
b1010 L
b1010 N
b1010 ]
b1001 B
b1001 M
b1001 o
b1001 z
1"
#9000
0"
#9500
b1110 C
b1110 e
b1110 n
0*
b11 x
b1110 >
b1110 b
b1110 c
b100 +
b100 Y
b100 &"
b110 F
b110 H
b110 s
b1000110 O
06
b0 3
b0 S
b0 h
b1 .
b1 T
b1 X
b1001 ;
b1001 G
b1001 Z
b100011 d
b11 E
b11 J
b11 f
b11 u
b11 ,
b11 m
b11 %"
b100111000110 a
b100 V
b11 U
b110 }
b110 r
b110 q
b1000110 7
b1000110 [
b1000110 )"
b1000110 ("
b0 Q
b1001 /
b1001 \
b1001 v
b1001 ""
b11 $"
b100011 0
b100011 I
b100011 !"
b10 #"
b1110 ?
b1110 _
b1110 `
b11 1
b11 j
b11 k
b100111000110 !
b100111000110 8
b100111000110 {
b1010100 @
b1010100 P
b1010100 ^
b1110 g
b1110 A
b1110 L
b1110 N
b1110 ]
b1101 B
b1101 M
b1101 o
b1101 z
1"
#10000
0"
#10500
x*
b101 ,
b101 m
b101 %"
bx 1
bx j
bx k
bx x
b1010 C
b1010 e
b1010 n
b0 +
b0 Y
b0 &"
1D
b1000 O
b0 ;
b0 G
b0 Z
b1010 d
bx E
bx J
bx f
bx u
b1111 >
b1111 b
b1111 c
b1110000001000 a
b0 V
b0 U
b1000 }
b1000 r
b1000 q
b1000 7
b1000 [
b1000 )"
b1000 ("
b0 /
b0 \
b0 v
b0 ""
b0 $"
b1010 0
b1010 I
b1010 !"
b111 #"
b1111 ?
b1111 _
b1111 `
b1110000001000 !
b1110000001000 8
b1110000001000 {
b10111 @
b10111 P
b10111 ^
b1111 g
b1111 A
b1111 L
b1111 N
b1111 ]
b1110 B
b1110 M
b1110 o
b1110 z
1"
#11000
0"
#11500
b101 ,
b101 m
b101 %"
b1011 C
b1011 e
b1011 n
0*
b101 1
b101 j
b101 k
b101 x
b100 +
b100 Y
b100 &"
0D
b0 F
b0 H
b0 s
b10 O
b11 =
b11 R
b11 p
b11 |
1<
b0 .
b0 T
b0 X
b11 d
b101 E
b101 J
b101 f
b101 u
b1011 >
b1011 b
b1011 c
b1001000000010 a
b100 U
b10 }
b110010 r
b10 q
b10 7
b10 [
b10 )"
b10 ("
b111 Q
b100 $"
b11 0
b11 I
b11 !"
b100 #"
b10 ;
b10 G
b10 Z
b1011 ?
b1011 _
b1011 `
b1111001000000010 !
b1111001000000010 8
b1111001000000010 {
b11 /
b11 \
b11 v
b11 ""
b1101 @
b1101 P
b1101 ^
b1011 g
b1011 A
b1011 L
b1011 N
b1011 ]
b1010 B
b1010 M
b1010 o
b1010 z
1"
#12000
0"
